{
  "profile": {
    "uuid": "1a5af54b-6fd4-4f86-ad9c-74881d4ea436",
    "metadata": {
      "title": "example Inc. level 1 controls profile.",
      "last-modified": "2023-12-13T20:08:04.921770+00:00",
      "version": "0.0.1",
      "oscal-version": "1.0.4"
    },
    "imports": [
      {
        "href": "trestle://catalogs/example_custom_controls/catalog.json",
        "include-controls": [
          {
            "with-ids": [
              "cc-1"
            ]
          }
        ]
      }
    ],
    "merge": {
      "combine": {
        "method": "merge"
      },
      "as-is": true
    },
    "modify": {
      "set-parameters": [
        {
          "param-id": "cc-1_prm_1",
          "values": [
            "1.0"
          ]
        }
      ]
    }
  }
}